{"_type":"export","__export_format":4,"__export_date":"2021-11-20T01:51:25.232Z","__export_source":"insomnia.desktop.app:v2021.6.0","resources":[{"_id":"req_12c60b8e201f4c569db1d93ff2f5a886","parentId":"fld_aabf0ca984c94d818895b093de235c08","modified":1637372842418,"created":1637307763406,"url":"localhost:8080/api/User","name":"Get List User","description":"","method":"GET","body":{},"parameters":[{"id":"pair_f27503f1b26545fe934c1ac5c58ccc1e","name":"page","value":"2","description":""},{"id":"pair_f0472eaa5fbf4b148210718fc72fc957","name":"per_page","value":"3","description":""}],"headers":[],"authentication":{},"metaSortKey":-1637307857182,"isPrivate":false,"settingStoreCookies":true,"settingSendCookies":true,"settingDisableRenderRequestBody":false,"settingEncodeUrl":true,"settingRebuildPath":true,"settingFollowRedirects":"global","_type":"request"},{"_id":"fld_aabf0ca984c94d818895b093de235c08","parentId":"wrk_1c757e7ba2ba4d79848dc30792b1fb7d","modified":1637307857232,"created":1637307857232,"name":"User","description":"","environment":{},"environmentPropertyOrder":null,"metaSortKey":-1637307857232,"_type":"request_group"},{"_id":"wrk_1c757e7ba2ba4d79848dc30792b1fb7d","parentId":null,"modified":1637373018599,"created":1637307711977,"name":"API_TP","description":"","scope":"collection","_type":"workspace"},{"_id":"req_539a8b2d1e9849ac9e8219570b8102f1","parentId":"fld_aabf0ca984c94d818895b093de235c08","modified":1637372809782,"created":1637308531011,"url":"localhost:8080/api/User","name":"Get User By Role","description":"","method":"GET","body":{},"parameters":[],"headers":[],"authentication":{},"metaSortKey":-1637307857132,"isPrivate":false,"settingStoreCookies":true,"settingSendCookies":true,"settingDisableRenderRequestBody":false,"settingEncodeUrl":true,"settingRebuildPath":true,"settingFollowRedirects":"global","_type":"request"},{"_id":"req_17a79e661a1c4a92a509fa0b8f17f539","parentId":"fld_aabf0ca984c94d818895b093de235c08","modified":1637372962103,"created":1637308661337,"url":"localhost:8080/api/User","name":"Add User","description":"","method":"POST","body":{"mimeType":"application/json","text":"{\n    \"Usuario_ID\": \"amparooliver\",\n    \"Usuario_Contra\": \"contrasenha\",\n\t\t\"email\": \"example@email.com\"\n}"},"parameters":[],"headers":[{"name":"Content-Type","value":"application/json","id":"pair_63ebbb12ccfb429a9600204fc4881001"}],"authentication":{},"metaSortKey":-1637307857082,"isPrivate":false,"settingStoreCookies":true,"settingSendCookies":true,"settingDisableRenderRequestBody":false,"settingEncodeUrl":true,"settingRebuildPath":true,"settingFollowRedirects":"global","_type":"request"},{"_id":"env_3b1ee7bd35965adeac536a54b2fd9033e496b205","parentId":"wrk_1c757e7ba2ba4d79848dc30792b1fb7d","modified":1637307711990,"created":1637307711990,"name":"Base Environment","data":{},"dataPropertyOrder":null,"color":null,"isPrivate":false,"metaSortKey":1637307711990,"_type":"environment"},{"_id":"jar_3b1ee7bd35965adeac536a54b2fd9033e496b205","parentId":"wrk_1c757e7ba2ba4d79848dc30792b1fb7d","modified":1637307711994,"created":1637307711994,"name":"Default Jar","cookies":[],"_type":"cookie_jar"},{"_id":"spc_f804d92086574b21a7073a1b58b58dbe","parentId":"wrk_1c757e7ba2ba4d79848dc30792b1fb7d","modified":1637307711978,"created":1637307711978,"fileName":"Taller de API","contents":"","contentType":"yaml","_type":"api_spec"}]}